lsports/__init__.py
lsports/__main__.py
lsports/_common.py
lsports/_linux.py
lsports/_osx.py
lsports/_posix.py
lsports/_windows.py
lsports/py.typed
lsports-0.1.0.dist-info/METADATA
lsports-0.1.0.dist-info/WHEEL
lsports-0.1.0.dist-info/licenses/LICENSE
lsports-0.1.0.dist-info/RECORD
