Metadata-Version: 2.1
Name: lsports
Version: 0.1.0
Summary: List serial ports.
Project-URL: Homepage, https://github.com/hamdanal/lsports
Project-URL: Documentation, https://github.com/hamdanal/lsports#lsports
Project-URL: Issue-Tracker, https://github.com/hamdanal/lsports/issues
Author-email: Ali Hamdan <ali.hamdan.dev@gmail.com>
License-Expression: MIT
License-File: LICENSE
Keywords: COM,USB,list-ports,lsports,serial
Classifier: Development Status :: 3 - Alpha
Classifier: License :: OSI Approved :: MIT License
Classifier: Operating System :: OS Independent
Classifier: Programming Language :: Python :: 3.7
Classifier: Programming Language :: Python :: 3.8
Classifier: Programming Language :: Python :: 3.9
Classifier: Programming Language :: Python :: 3.10
Classifier: Programming Language :: Python :: 3.11
Classifier: Programming Language :: Python :: 3.12
Requires-Python: >=3.7
